cryptofiles/__init__.py
cryptofiles/cryptofiles.py
datacoin/__init__.py
datacoin/datacoin.py
cryptofiles-0.1.1.dist-info/LICENSE
cryptofiles-0.1.1.dist-info/METADATA
cryptofiles-0.1.1.dist-info/WHEEL
cryptofiles-0.1.1.dist-info/top_level.txt
cryptofiles-0.1.1.dist-info/RECORD
