Metadata-Version: 2.1
Name: cryptofiles
Version: 0.1.1
Summary: for working with blockchained files
Home-page: https://github.com/xloem/cryptofiles
Author: xloem
Author-email: 0xloem@gmail.com
License: UNKNOWN
Platform: UNKNOWN
Classifier: Programming Language :: Python :: 3
Classifier: Operating System :: OS Independent
Requires-Python: >=3.6
